evidencedev/__init__.py
evidencedev/evidencedev.py
evidencedev_py-0.1.0.dist-info/LICENSE.MD
evidencedev_py-0.1.0.dist-info/METADATA
evidencedev_py-0.1.0.dist-info/WHEEL
evidencedev_py-0.1.0.dist-info/top_level.txt
evidencedev_py-0.1.0.dist-info/RECORD
