Metadata-Version: 2.1
Name: evidencedev-py
Version: 0.1.0
Summary: A python wrapper to pull data from websites created in evidence.dev
Home-page: https://github.com/AmunAnalytics/evidencedev-py
Author: Frank Boerman
Author-email: frank@fboerman.nl
License: MIT
Keywords: evidence.dev data datascience api
Classifier: Development Status :: 5 - Production/Stable
Classifier: Intended Audience :: Developers
Classifier: Topic :: Scientific/Engineering
Classifier: License :: OSI Approved :: MIT License
Classifier: Programming Language :: Python :: 3.9
Classifier: Programming Language :: Python :: 3.10
Classifier: Programming Language :: Python :: 3.11
License-File: LICENSE.MD
Requires-Dist: requests
Requires-Dist: pandas
Requires-Dist: pyarrow
